mcp_jsondiff_kel/__init__.py
mcp_jsondiff_kel/__main__.py
mcp_jsondiff_kel/server.py
mcp_jsondiff_kel-0.1.5.dist-info/METADATA
mcp_jsondiff_kel-0.1.5.dist-info/WHEEL
mcp_jsondiff_kel-0.1.5.dist-info/entry_points.txt
mcp_jsondiff_kel-0.1.5.dist-info/RECORD
